{
  "id": "a24c289ae164",
  "slug": "코인원-신규-서비스-고도화-po디자이너-뽑는다-172520",
  "channelId": "CRYPTO",
  "category": "crypto",
  "publishedAt": "2026-06-15T03:23:27.410Z",
  "updatedAt": "2026-06-15T03:23:27.410Z",
  "sourceName": "",
  "sourceUrl": "",
  "canonicalUrl": "https://www.mk.co.kr/news/stock/12074158",
  "titleFingerprint": "e67c422d585cf1345eaf3cc4ef0aa52978959484",
  "dedupKeys": [
    "a24c289ae164fb0b552a7174cda052b6079de237",
    "e67c422d585cf1345eaf3cc4ef0aa52978959484",
    "233a658d9cebc7990a9dbcd5c01418a746e7140a"
  ],
  "imageUrl": "/images/articles/a24c289ae164.png",
  "i18n": {
    "ko": {
      "title": "코인원 채용 확대, 신규 서비스 고도화 위해 PO·디자이너 모집",
      "excerpt": "국내 원화 가상자산 거래소 코인원이 내달 6일까지 프로덕트 오너와 디자이너를 모집하며 신규 서비스 고도화와 법제화 환경에 맞춘 제품 경쟁력 강화에 나선다.",
      "metaDescription": "코인원이 내달 6일까지 PO와 디자이너를 모집한다. 간편지원과 48시간 내 결과 안내를 도입해 가상자산 법제화에 맞춘 서비스 고도화를 추진한다.",
      "summary": "코인원이 신규 서비스 고도화를 위해 프로덕트 오너와 디자이너 채용에 나섰다. 모집 기한은 내달 6일까지이며 간편지원 절차와 48시간 내 결과 안내가 적용된다. 가상자산 법제화가 본격화되는 국내 시장에서 제품 기획, 사용자 경험, 서비스 안정성을 강화하려는 인재 확보 전략이다.",
      "body": "코인원이 신규 서비스 고도화를 위해 프로덕트 오너(PO)와 디자이너 채용을 확대한다. 국내 원화 가상자산 거래소 간 경쟁이 수수료와 상장 종목 중심에서 제품 완성도, 사용자 경험, 규제 대응 역량으로 이동하는 가운데, 코인원은 핵심 서비스 기획과 디자인 역량을 보강해 다음 단계의 성장 기반을 다진다.\n\n## 내달 6일까지 PO·디자이너 모집\n\n코인원은 내달 6일까지 PO와 디자이너 직군을 모집한다. 이번 채용은 신규 서비스 고도화에 직접 투입될 인재 확보에 초점이 맞춰졌다. PO는 거래소 서비스의 방향성, 기능 우선순위, 이용자 흐름, 사업 요구사항을 조율하는 역할을 맡는다. 디자이너는 투자자가 실제로 접하는 화면과 정보 구조, 거래 편의성, 브랜드 경험을 개선하는 업무를 수행한다.\n\n채용 과정에는 간편지원 방식이 도입됐다. 지원자가 복잡한 절차에 막혀 이탈하지 않도록 진입 장벽을 낮춘 것이 특징이다. 지원 이후 48시간 안에 결과를 안내하는 운영 방식도 적용된다. 인재 확보 경쟁이 치열한 국내 정보기술·핀테크 시장에서 빠른 피드백은 지원자 경험을 좌우하는 핵심 요소로 꼽힌다. 코인원은 채용 단계부터 속도와 명확성을 높여 우수 인재와의 접점을 넓힌다.\n\n## 법제화 국면에서 제품 경쟁력 강화\n\n이번 채용은 국내 가상자산 시장의 제도화 흐름과 맞물려 있다. 가상자산 관련 법제화가 본격화되면서 거래소는 단순 매매 중개를 넘어 투자자 보호, 정보 제공, 서비스 안정성, 내부통제 체계를 제품 안에 녹여야 하는 과제를 안고 있다. 이용자는 빠른 주문 처리뿐 아니라 명확한 고지, 쉬운 자산 확인, 안전한 인증 절차, 직관적인 위험 안내를 요구한다.\n\n원화 거래소는 국내 투자자가 원화를 직접 입출금해 가상자산을 사고파는 핵심 접점이다. 따라서 서비스 화면의 작은 변화도 투자 판단과 이용자 신뢰에 영향을 준다. PO와 디자이너 충원은 단순 인력 보강이 아니라 거래소의 제품 운영 방식 전반을 고도화하는 작업이다. 특히 규제 준수와 사용자 편의성을 동시에 만족시키는 설계 역량이 중요해지고 있다.\n\n## 국내 투자자 영향과 향후 전망\n\n국내 투자자 입장에서는 이번 채용이 향후 코인원 서비스의 사용성 개선으로 이어질 가능성이 크다. 신규 서비스가 고도화되면 자산 현황 파악, 거래 화면 이동, 상품 정보 확인, 고객 지원 접근성이 개선될 수 있다. 복잡한 가상자산 정보를 더 쉽게 이해하도록 만드는 설계는 초보 투자자와 장기 이용자 모두에게 중요한 요소다.\n\n거래소 업계에서는 인재 확보가 곧 경쟁력으로 연결된다. 법제화 이후에는 상장 관리, 투자자 보호, 보안, 데이터 기반 서비스 개선 역량이 거래소 평가의 핵심 기준이 될 전망이다. 코인원은 PO와 디자이너 채용을 통해 규제 환경 변화에 맞춘 제품 체질 개선을 추진한다. 국내 가상자산 시장이 성숙 단계로 접어들수록 거래소의 차별화 포인트는 더 정교한 서비스 경험과 신뢰 가능한 운영 능력으로 압축될 전망이다.",
      "keywords": [
        "코인원",
        "코인원 채용",
        "가상자산 거래소",
        "PO 채용",
        "디자이너 채용",
        "원화 거래소",
        "가상자산 법제화",
        "신규 서비스 고도화",
        "국내 crypto 시장",
        "코인원 채용 확대, 신규 서비스 고도"
      ],
      "faq": [
        {
          "q": "코인원은 어떤 직군을 채용하나요?",
          "a": "코인원은 신규 서비스 고도화를 위해 프로덕트 오너(PO)와 디자이너 직군을 모집한다."
        },
        {
          "q": "코인원 채용 지원 기한은 언제까지인가요?",
          "a": "이번 PO·디자이너 모집은 내달 6일까지 진행된다."
        },
        {
          "q": "이번 채용의 핵심 목적은 무엇인가요?",
          "a": "가상자산 법제화 환경에 맞춰 제품 기획, 사용자 경험, 서비스 완성도를 높이기 위한 인재 확보가 핵심 목적이다."
        }
      ]
    }
  }
}